nersi/__init__.py
nersi-0.1.1.dist-info/LICENSE
nersi-0.1.1.dist-info/WHEEL
nersi-0.1.1.dist-info/METADATA
nersi-0.1.1.dist-info/RECORD
